{
  "collectionName": "components_practical_reviews",
  "info": {
    "name": "review",
    "icon": "angry",
    "description": ""
  },
  "options": {},
  "attributes": {
    "slide": {
      "type": "component",
      "repeatable": true,
      "component": "practical.slide"
    },
    "name": {
      "type": "string"
    },
    "image": {
      "model": "file",
      "via": "related",
      "allowedTypes": [
        "images",
        "files",
        "videos"
      ],
      "plugin": "upload",
      "required": false,
      "pluginOptions": {}
    }
  }
}
